korea_news_crawler/__init__.py
korea_news_crawler/articlecrawler.py
korea_news_crawler/articleparser.py
korea_news_crawler/exceptions.py
korea_news_crawler/sample.py
korea_news_crawler/sportcrawler.py
korea_news_crawler/sports_crawler_sample.py
korea_news_crawler/writer.py
KoreaNewsCrawler-1.51.dist-info/LICENSE
KoreaNewsCrawler-1.51.dist-info/METADATA
KoreaNewsCrawler-1.51.dist-info/WHEEL
KoreaNewsCrawler-1.51.dist-info/top_level.txt
KoreaNewsCrawler-1.51.dist-info/RECORD
