Metadata-Version: 2.1
Name: KoreaNewsCrawler
Version: 1.51
Summary: Crawl the korean news
Home-page: https://github.com/lumyjuwon/KoreaNewsCrawler
Author: lumyjuwon
Author-email: lumyjuwon@gmail.com
License: UNKNOWN
Download-URL: https://github.com/lumyjuwon/KoreaNewsCrawler/archive/1.51.tar.gz
Keywords: crawl,KoreaNews,crawler
Platform: UNKNOWN
Classifier: Programming Language :: Python :: 3.6
Requires-Python: >=3.6
License-File: LICENSE
Requires-Dist: requests
Requires-Dist: beautifulsoup4
